netbeansifier/__init__.py
netbeansifier/__main__.py
netbeansifier/netbeansify.py
netbeansifier/netbeanz.png
netbeansifier/template/build.xml
netbeansifier/template/manifest.mf
netbeansifier/template/nbproject/build-impl.xml
netbeansifier/template/nbproject/genfiles.properties
netbeansifier/template/nbproject/project.properties
netbeansifier/template/nbproject/project.xml
netbeansifier-1.0.1.dist-info/LICENSE
netbeansifier-1.0.1.dist-info/METADATA
netbeansifier-1.0.1.dist-info/WHEEL
netbeansifier-1.0.1.dist-info/entry_points.txt
netbeansifier-1.0.1.dist-info/top_level.txt
netbeansifier-1.0.1.dist-info/RECORD
