Metadata-Version: 2.1
Name: netbeansifier
Version: 1.0.1
Summary: Simple and dumb Python script that packages up Java files into a basic NetBeans project for ICS4U.
Home-page: https://github.com/tylertian123/netbeansifier
Author: Tyler Tian
Author-email: tylertian123@gmail.com
License: UNKNOWN
Keywords: netbeans
Platform: UNKNOWN
Classifier: Programming Language :: Python :: 3
Classifier: License :: OSI Approved :: MIT License
Classifier: Operating System :: OS Independent
Requires-Python: >=3.6
Requires-Dist: pathspec
